cradle/__init__.py
cradle/cli.py
cradle/config.py
qcradle-0.4.1.dist-info/METADATA
qcradle-0.4.1.dist-info/WHEEL
qcradle-0.4.1.dist-info/entry_points.txt
qcradle-0.4.1.dist-info/licenses/LICENSE
qcradle-0.4.1.dist-info/RECORD
