Metadata-Version: 2.4
Name: qCradle
Version: 0.4.1
Summary: CLI to create repos
Project-URL: repository, https://github.com/tschm/cradle
Author-email: Thomas Schmelzer <thomas.schmelzer@gmail.com>
License-File: LICENSE
Requires-Python: >=3.10
Requires-Dist: copier>=9.8.0
Requires-Dist: pyyaml==6.0.3
Requires-Dist: rich>=13.7.0
Requires-Dist: typer>=0.9.0
Provides-Extra: dev
Requires-Dist: marimo==0.18.4; extra == 'dev'
Requires-Dist: pre-commit==4.5.0; extra == 'dev'
Requires-Dist: pytest-cov==7.0.0; extra == 'dev'
Requires-Dist: pytest-mock==3.15.1; extra == 'dev'
Requires-Dist: pytest==9.0.2; extra == 'dev'
